py_testproject/__init__.py
py_testproject/console.py
py_testproject/wikipedia.py
py_testproject-0.2.0.dist-info/entry_points.txt
py_testproject-0.2.0.dist-info/LICENSE
py_testproject-0.2.0.dist-info/WHEEL
py_testproject-0.2.0.dist-info/METADATA
py_testproject-0.2.0.dist-info/RECORD
